{
  "passage_id": "attention-as-lever-2cb4fd2bfaeb",
  "resonates": [
    {
      "timestamp": "2026-05-12T23:33:35.458Z",
      "user_fingerprint": "5bda559a-ffeb-4749-a9a8-2641458d3258",
      "selector": {
        "type": "TextQuoteSelector",
        "exact": "What you repeatedly attend to gets easier to notice, easier to return to, and easier to believe.",
        "prefix": "ve Things to Understand\n\n\nAttention funds reality\n",
        "suffix": " Your brain strengthens the pathways you use most.",
        "startOffset": 2346,
        "endOffset": 2442
      }
    }
  ]
}
